.gitignore
.gitlab-ci.yml
.gitmodules
Makefile
NEWS.txt
README.md
SoftPosit.patch
berkeley-softfloat.patch
setup.py
doc/frsqrt.rst
src/ieee754/__init__.py
src/ieee754/pipeline.py
src/ieee754/add/__init__.py
src/ieee754/add/add_shift_experiment.py
src/ieee754/add/dual_add_experiment.py
src/ieee754/add/example_comb_pipe.py
src/ieee754/add/f.py
src/ieee754/add/fifo.py
src/ieee754/add/fsqr.py
src/ieee754/add/function_unit.py
src/ieee754/add/hmc_backed_fifo_tb.py
src/ieee754/add/inputgroup.py
src/ieee754/add/original_single_pipe.py
src/ieee754/add/pipeline_example.py
src/ieee754/add/pipeline_example2.py
src/ieee754/add/record_experiment.py
src/ieee754/add/rstation_row.py
src/ieee754/add/run_test.py
src/ieee754/add/slice_repro.py
src/ieee754/add/test_add_pipe.py
src/ieee754/add/test_dual.py
src/ieee754/add/test_fpdiv_pipe.py
src/ieee754/add/test_fpnum.py
src/ieee754/add/test_inputgroup.py
src/ieee754/add/test_multishift.py
src/ieee754/add/test_orgate.py
src/ieee754/add/test_state_add.py
src/ieee754/add/test_syncops.py
src/ieee754/cordic/fp_pipe_data.py
src/ieee754/cordic/fp_pipe_init_stages.py
src/ieee754/cordic/fp_pipeline.py
src/ieee754/cordic/fpsin_cos.py
src/ieee754/cordic/pipe_data.py
src/ieee754/cordic/renormalize.py
src/ieee754/cordic/sin_cos.py
src/ieee754/cordic/sin_cos_pipe_stage.py
src/ieee754/cordic/sin_cos_pipeline.py
src/ieee754/cordic/test/python_sin_cos.py
src/ieee754/cordic/test/test_fp_pipe.py
src/ieee754/cordic/test/test_fpsin_cos.py
src/ieee754/cordic/test/test_sincos.py
src/ieee754/cordic/test/test_software.py
src/ieee754/div_rem_sqrt_rsqrt/__init__.py
src/ieee754/div_rem_sqrt_rsqrt/algorithm.py
src/ieee754/div_rem_sqrt_rsqrt/algorithm.pyi
src/ieee754/div_rem_sqrt_rsqrt/core.py
src/ieee754/div_rem_sqrt_rsqrt/div_pipe.py
src/ieee754/div_rem_sqrt_rsqrt/test_algorithm.py
src/ieee754/div_rem_sqrt_rsqrt/test_core.py
src/ieee754/fclass/__init__.py
src/ieee754/fclass/fclass.py
src/ieee754/fclass/pipeline.py
src/ieee754/fclass/test/__init__.py
src/libresoc_ieee754fpu.egg-info/PKG-INFO
src/libresoc_ieee754fpu.egg-info/SOURCES.txt
src/libresoc_ieee754fpu.egg-info/dependency_links.txt
src/libresoc_ieee754fpu.egg-info/not-zip-safe
src/libresoc_ieee754fpu.egg-info/requires.txt
src/libresoc_ieee754fpu.egg-info/top_level.txt