Metadata-Version: 1.1
Name: libresoc-ieee754fpu
Version: 0.0.1
Summary: A nmigen (HDL) IEEE754 Floating-Point library
Home-page: http://git.libre-soc.org/?p=ieee754fpu.git
Author: Luke Kenneth Casson Leighton
Author-email: lkcl@libre-soc.org
License: GPLv3+
Keywords: nmigen ieee754
Platform: UNKNOWN
Classifier: Topic :: Software Development :: Libraries
Classifier: License :: OSI Approved :: GNU Lesser General Public License v3 or later (LGPLv3+)
Classifier: Programming Language :: Python :: 3
